Metadata-Version: 1.0
Name: stylelens-feature
Version: 1.0.12
Summary: stylelens-feature
Home-page: UNKNOWN
Author: UNKNOWN
Author-email: master@bluehack.net
License: UNKNOWN
Keywords: BlueLens,stylelens-feature
Platform: UNKNOWN
